caduceus/__init__.py
caduceus/cli.py
caduceus-0.0.11.dist-info/LICENSE
caduceus-0.0.11.dist-info/WHEEL
caduceus-0.0.11.dist-info/METADATA
caduceus-0.0.11.dist-info/RECORD
