Metadata-Version: 2.1
Name: caduceus
Version: 0.0.11
Summary: A server that will alert you if your tasks have not run.
Home-page: https://gitlab.com/stavros/caduceus/
License: UNKNOWN
Author: Stavros Korokithakis
Author-email: hi@stavros.io
